ghalatawi/__init__.py
ghalatawi/ar_ghalat.py
ghalatawi/autocorrector.py
ghalatawi/ghalat_const.py
ghalatawi/data/arabic0.2.acl
ghalatawi-0.3.dist-info/AUTHORS.md
ghalatawi-0.3.dist-info/LICENSE
ghalatawi-0.3.dist-info/METADATA
ghalatawi-0.3.dist-info/WHEEL
ghalatawi-0.3.dist-info/top_level.txt
ghalatawi-0.3.dist-info/RECORD
