Metadata-Version: 2.1
Name: ghalatawi
Version: 0.3
Summary: ghalatawi: Arabic autocorrect library
Home-page: http://ghalatawi.sourceforge.net/
Author: Taha Zerrouki
Author-email: taha.zerrouki@gmail.com
License: GPL
Platform: UNKNOWN
Classifier: Development Status :: 5 - Production/Stable
Classifier: Intended Audience :: End Users/Desktop
Classifier: Operating System :: OS Independent
Classifier: Programming Language :: Python
Requires-Dist: pyarabic (>=0.6.8)
